tinycards/__init__.py
tinycards/client/__init__.py
tinycards/client/tinycards.py
tinycards/model/__init__.py
tinycards/model/card.py
tinycards/model/concept.py
tinycards/model/deck.py
tinycards/model/fact.py
tinycards/model/favorite.py
tinycards/model/searchable_data.py
tinycards/model/side.py
tinycards/model/trendable.py
tinycards/model/trendable_data.py
tinycards/model/user.py
tinycards/networking/__init__.py
tinycards/networking/form_utils.py
tinycards/networking/json_converter.py
tinycards/networking/rest_api.py
tinycards-0.2.dist-info/DESCRIPTION.rst
tinycards-0.2.dist-info/METADATA
tinycards-0.2.dist-info/RECORD
tinycards-0.2.dist-info/WHEEL
tinycards-0.2.dist-info/metadata.json
tinycards-0.2.dist-info/top_level.txt
