Metadata-Version: 2.0
Name: tinycards
Version: 0.2
Summary: An unofficial Python API for Tinycards by Duolingo
Home-page: https://github.com/floscha/tinycards-python-api
Author: Florian Schäfer
Author-email: florian.joh.schaefer@gmail.com
License: MIT
Platform: UNKNOWN
Requires-Dist: pytest
Requires-Dist: requests
